<?xml version="1.0"?>
<XmlLevelData xmlns:xsi="http://www.w3.org/2001/XMLSchema-instance" xmlns:xsd="http://www.w3.org/2001/XMLSchema">
  <waypoints>
    <paths>
      <nodes>
        <position>
          <X>-2.071535</X>
          <Y>9.430093</Y>
        </position>
        <height>0</height>
        <airborne>false</airborne>
      </nodes>
      <nodes>
        <position>
          <X>1.14722073</X>
          <Y>9.480872</Y>
        </position>
        <height>0</height>
        <airborne>false</airborne>
      </nodes>
      <nodes>
        <position>
          <X>1.23247921</X>
          <Y>12.812789</Y>
        </position>
        <height>0</height>
        <airborne>false</airborne>
      </nodes>
      <edges>
        <node0>0</node0>
        <node1>1</node1>
        <direction>3</direction>
      </edges>
      <edges>
        <node0>1</node0>
        <node1>2</node1>
        <direction>3</direction>
      </edges>
      <color>Red</color>
      <roadName />
    </paths>
    <paths>
      <nodes>
        <position>
          <X>-8.290944</X>
          <Y>15.3196144</Y>
        </position>
        <height>0</height>
        <airborne>false</airborne>
      </nodes>
      <nodes>
        <position>
          <X>-8.335352</X>
          <Y>18.8047028</Y>
        </position>
        <height>0</height>
        <airborne>false</airborne>
      </nodes>
      <nodes>
        <position>
          <X>-4.85822153</X>
          <Y>18.92691</Y>
        </position>
        <height>0</height>
        <airborne>false</airborne>
      </nodes>
      <edges>
        <node0>0</node0>
        <node1>1</node1>
        <direction>3</direction>
      </edges>
      <edges>
        <node0>1</node0>
        <node1>2</node1>
        <direction>3</direction>
      </edges>
      <color>White</color>
      <roadName />
    </paths>
  </waypoints>
  <actor>
    <position>
      <X>0.686224</X>
      <Y>10.8081188</Y>
      <Z>0.54719615</Z>
    </position>
    <orientation>1.564821</orientation>
    <heightOffset>0</heightOffset>
    <color>White</color>
    <tintable>true</tintable>
    <creatableId>00000000-0000-0000-0000-000000000000</creatableId>
    <creatableName>Coin 1</creatableName>
    <brain StartTaskId="-1" ActiveTaskId="-1">
      <uniqueNum>179139</uniqueNum>
      <tasks>
        <Task upid="task.managed0">
          <reflexes />
        </Task>
        <Task upid="task.managed1">
          <reflexes />
        </Task>
        <Task upid="task.managed2">
          <reflexes />
        </Task>
        <Task upid="task.managed3">
          <reflexes />
        </Task>
        <Task upid="task.managed4">
          <reflexes />
        </Task>
        <Task upid="task.managed5">
          <reflexes />
        </Task>
        <Task upid="task.managed6">
          <reflexes />
        </Task>
        <Task upid="task.managed7">
          <reflexes />
        </Task>
        <Task upid="task.managed8">
          <reflexes />
        </Task>
        <Task upid="task.managed9">
          <reflexes />
        </Task>
        <Task upid="task.managed10">
          <reflexes />
        </Task>
        <Task upid="task.managed11">
          <reflexes />
        </Task>
      </tasks>
    </brain>
    <parameters>
      <uniqueNum>148190</uniqueNum>
      <immobile>false</immobile>
      <immobileNoRot>false</immobileNoRot>
      <invulnerable>false</invulnerable>
      <showSensors>false</showSensors>
      <showHitPoints>false</showHitPoints>
      <creatable>false</creatable>
      <mute>false</mute>
      <maxHitPoints>50</maxHitPoints>
      <blipDamage>5</blipDamage>
      <missileDamage>50</missileDamage>
      <movementSpeedModifier>1</movementSpeedModifier>
      <turningSpeedModifier>1</turningSpeedModifier>
      <linearAccelerationModifier>1</linearAccelerationModifier>
      <turningAccelerationModifier>1</turningAccelerationModifier>
      <verticalSpeedModifier>1</verticalSpeedModifier>
      <verticalAccelerationModifier>1</verticalAccelerationModifier>
      <blipReloadTime>0.05</blipReloadTime>
      <blipSpeed>10</blipSpeed>
      <blipRange>35</blipRange>
      <blipsInAir>40</blipsInAir>
      <beamReloadTime>0.025</beamReloadTime>
      <beamSpeed>10</beamSpeed>
      <beamDist>35</beamDist>
      <beamsInAir>2000</beamsInAir>
      <revealed>false</revealed>
      <missileReloadTime>3</missileReloadTime>
      <missileSpeed>6</missileSpeed>
      <missileRange>50</missileRange>
      <missilesInAir>4</missilesInAir>
      <missileTrails>true</missileTrails>
      <shieldEffects>true</shieldEffects>
      <invisible>false</invisible>
      <ignored>false</ignored>
      <camouflaged>false</camouflaged>
      <pushRange>15</pushRange>
      <pushStrength>50</pushStrength>
      <kickStrength>10</kickStrength>
      <kickRate>2</kickRate>
      <hearing>1</hearing>
      <loudness>1</loudness>
      <glowAmt>1</glowAmt>
      <glowLights>0</glowLights>
      <glowEmission>0</glowEmission>
      <displayLOS>false</displayLOS>
      <displayLOP>false</displayLOP>
      <displayCurrentPage>false</displayCurrentPage>
      <cameraMode>UserControlled</cameraMode>
      <coefficientOfRestitution>0.6</coefficientOfRestitution>
      <friction>0.9</friction>
      <lightRange>10</lightRange>
      <stayAboveWater>false</stayAboveWater>
      <maxCreated>1000</maxCreated>
      <rescale>1</rescale>
      <holdDistance>1</holdDistance>
      <_holdDistance>1</_holdDistance>
      <mass>0.1</mass>
      <heightOffset>-666</heightOffset>
      <nearByDistance>5</nearByDistance>
      <farAwayDistance>15</farAwayDistance>
    </parameters>
    <version>1</version>
    <typename>Coin</typename>
  </actor>
  <actor>
    <position>
      <X>-0.03831482</X>
      <Y>17.4366627</Y>
      <Z>1.14719617</Z>
    </position>
    <orientation>1.564821</orientation>
    <heightOffset>0</heightOffset>
    <color>Blue</color>
    <tintable>true</tintable>
    <creatableId>00000000-0000-0000-0000-000000000000</creatableId>
    <creatableName>Kodu 1</creatableName>
    <brain StartTaskId="-1" ActiveTaskId="-1">
      <uniqueNum>179140</uniqueNum>
      <tasks>
        <Task upid="task.managed0">
          <reflexes>
            <Reflex>
              <uniqueNum>179141</uniqueNum>
              <sensorUpid>sensor.always</sensorUpid>
              <actuatorUpid>actuator.score</actuatorUpid>
              <ParamInt>0</ParamInt>
              <ParamFloat>0</ParamFloat>
              <MaterialType>4096</MaterialType>
              <WaterType>-1</WaterType>
              <Indentation>0</Indentation>
              <ReScaleEnabled>false</ReScaleEnabled>
              <ReScale>1</ReScale>
              <HoldDistance>1</HoldDistance>
              <MaxHipoints>50</MaxHipoints>
              <MoveSpeedTileModifier>1</MoveSpeedTileModifier>
              <TurnSpeedTileModifier>1</TurnSpeedTileModifier>
              <WorldLightChangeEnabled>false</WorldLightChangeEnabled>
              <WorldLightChangeIndex>0</WorldLightChangeIndex>
              <WorldSkyChangeEnabled>false</WorldSkyChangeEnabled>
              <WorldSkyChangeIndex>0</WorldSkyChangeIndex>
              <SetWaterTypeIndex>-1</SetWaterTypeIndex>
              <filterUpids />
              <modifierUpids>
                <upid>modifier.scorebucket.color.purple</upid>
                <upid>modifier.100points</upid>
              </modifierUpids>
              <SayMode>1</SayMode>
              <SayJustification>Left</SayJustification>
              <SaidString />
              <SaidMode>1</SaidMode>
              <SaidJustification>Left</SaidJustification>
              <MicrobitPatterns />
            </Reflex>
            <Reflex>
              <uniqueNum>179146</uniqueNum>
              <sensorUpid>sensor.always</sensorUpid>
              <actuatorUpid>actuator.scoreset</actuatorUpid>
              <ParamInt>0</ParamInt>
              <ParamFloat>0</ParamFloat>
              <MaterialType>4096</MaterialType>
              <WaterType>-1</WaterType>
              <Indentation>0</Indentation>
              <ReScaleEnabled>false</ReScaleEnabled>
              <ReScale>1</ReScale>
              <HoldDistance>1</HoldDistance>
              <MaxHipoints>50</MaxHipoints>
              <MoveSpeedTileModifier>1</MoveSpeedTileModifier>
              <TurnSpeedTileModifier>1</TurnSpeedTileModifier>
              <WorldLightChangeEnabled>false</WorldLightChangeEnabled>
              <WorldLightChangeIndex>0</WorldLightChangeIndex>
              <WorldSkyChangeEnabled>false</WorldSkyChangeEnabled>
              <WorldSkyChangeIndex>0</WorldSkyChangeIndex>
              <SetWaterTypeIndex>-1</SetWaterTypeIndex>
              <filterUpids />
              <modifierUpids>
                <upid>modifier.scorebucket.color.red</upid>
                <upid>modifier.100points</upid>
              </modifierUpids>
              <SayMode>1</SayMode>
              <SayJustification>Left</SayJustification>
              <SaidString />
              <SaidMode>1</SaidMode>
              <SaidJustification>Left</SaidJustification>
              <MicrobitPatterns />
            </Reflex>
            <Reflex>
              <uniqueNum>179151</uniqueNum>
              <actuatorUpid>actuator.switchtask</actuatorUpid>
              <ParamInt>0</ParamInt>
              <ParamFloat>0</ParamFloat>
              <MaterialType>4096</MaterialType>
              <WaterType>-1</WaterType>
              <Indentation>1</Indentation>
              <ReScaleEnabled>false</ReScaleEnabled>
              <ReScale>1</ReScale>
              <HoldDistance>1</HoldDistance>
              <MaxHipoints>50</MaxHipoints>
              <MoveSpeedTileModifier>1</MoveSpeedTileModifier>
              <TurnSpeedTileModifier>1</TurnSpeedTileModifier>
              <WorldLightChangeEnabled>false</WorldLightChangeEnabled>
              <WorldLightChangeIndex>0</WorldLightChangeIndex>
              <WorldSkyChangeEnabled>false</WorldSkyChangeEnabled>
              <WorldSkyChangeIndex>0</WorldSkyChangeIndex>
              <SetWaterTypeIndex>-1</SetWaterTypeIndex>
              <filterUpids />
              <modifierUpids>
                <upid>modifier.taskb</upid>
              </modifierUpids>
              <SayMode>1</SayMode>
              <SayJustification>Left</SayJustification>
              <SaidString />
              <SaidMode>1</SaidMode>
              <SaidJustification>Left</SaidJustification>
              <MicrobitPatterns />
            </Reflex>
          </reflexes>
        </Task>
        <Task upid="task.managed1">
          <reflexes>
            <Reflex>
              <uniqueNum>179154</uniqueNum>
              <sensorUpid>sensor.keyboard</sensorUpid>
              <actuatorUpid>actuator.movement</actuatorUpid>
              <ParamInt>0</ParamInt>
              <ParamFloat>0</ParamFloat>
              <MaterialType>4096</MaterialType>
              <WaterType>-1</WaterType>
              <Indentation>0</Indentation>
              <ReScaleEnabled>false</ReScaleEnabled>
              <ReScale>1</ReScale>
              <HoldDistance>1</HoldDistance>
              <MaxHipoints>50</MaxHipoints>
              <MoveSpeedTileModifier>1</MoveSpeedTileModifier>
              <TurnSpeedTileModifier>1</TurnSpeedTileModifier>
              <WorldLightChangeEnabled>false</WorldLightChangeEnabled>
              <WorldLightChangeIndex>0</WorldLightChangeIndex>
              <WorldSkyChangeEnabled>false</WorldSkyChangeEnabled>
              <WorldSkyChangeIndex>0</WorldSkyChangeIndex>
              <SetWaterTypeIndex>-1</SetWaterTypeIndex>
              <filterUpids>
                <upid>filter.WASDKeys</upid>
              </filterUpids>
              <modifierUpids />
              <SayMode>1</SayMode>
              <SayJustification>Left</SayJustification>
              <SaidString />
              <SaidMode>1</SaidMode>
              <SaidJustification>Left</SaidJustification>
              <MicrobitPatterns />
            </Reflex>
            <Reflex>
              <uniqueNum>179166</uniqueNum>
              <sensorUpid>sensor.terrain</sensorUpid>
              <ParamInt>0</ParamInt>
              <ParamFloat>0</ParamFloat>
              <MaterialType>31</MaterialType>
              <WaterType>-1</WaterType>
              <Indentation>0</Indentation>
              <ReScaleEnabled>false</ReScaleEnabled>
              <ReScale>1</ReScale>
              <HoldDistance>1</HoldDistance>
              <MaxHipoints>50</MaxHipoints>
              <MoveSpeedTileModifier>1</MoveSpeedTileModifier>
              <TurnSpeedTileModifier>1</TurnSpeedTileModifier>
              <WorldLightChangeEnabled>false</WorldLightChangeEnabled>
              <WorldLightChangeIndex>0</WorldLightChangeIndex>
              <WorldSkyChangeEnabled>false</WorldSkyChangeEnabled>
              <WorldSkyChangeIndex>0</WorldSkyChangeIndex>
              <SetWaterTypeIndex>-1</SetWaterTypeIndex>
              <filterUpids>
                <upid>filter.terrain</upid>
                <upid>filter.not</upid>
              </filterUpids>
              <modifierUpids />
              <SayMode>1</SayMode>
              <SayJustification>Left</SayJustification>
              <SaidString />
              <SaidMode>1</SaidMode>
              <SaidJustification>Left</SaidJustification>
              <MicrobitPatterns />
            </Reflex>
            <Reflex>
              <uniqueNum>179170</uniqueNum>
              <sensorUpid>sensor.keyboard</sensorUpid>
              <actuatorUpid>actuator.shoot2</actuatorUpid>
              <ParamInt>0</ParamInt>
              <ParamFloat>0</ParamFloat>
              <MaterialType>4096</MaterialType>
              <WaterType>-1</WaterType>
              <Indentation>1</Indentation>
              <ReScaleEnabled>false</ReScaleEnabled>
              <ReScale>1</ReScale>
              <HoldDistance>1</HoldDistance>
              <MaxHipoints>50</MaxHipoints>
              <MoveSpeedTileModifier>1</MoveSpeedTileModifier>
              <TurnSpeedTileModifier>1</TurnSpeedTileModifier>
              <WorldLightChangeEnabled>false</WorldLightChangeEnabled>
              <WorldLightChangeIndex>0</WorldLightChangeIndex>
              <WorldSkyChangeEnabled>false</WorldSkyChangeEnabled>
              <WorldSkyChangeIndex>0</WorldSkyChangeIndex>
              <SetWaterTypeIndex>-1</SetWaterTypeIndex>
              <filterUpids>
                <upid>filter.Spacekey</upid>
              </filterUpids>
              <modifierUpids>
                <upid>modifier.projectile.blip</upid>
                <upid>modifier.once</upid>
              </modifierUpids>
              <SayMode>1</SayMode>
              <SayJustification>Left</SayJustification>
              <SaidString />
              <SaidMode>1</SaidMode>
              <SaidJustification>Left</SaidJustification>
              <MicrobitPatterns />
            </Reflex>
            <Reflex>
              <uniqueNum>179184</uniqueNum>
              <actuatorUpid>actuator.unscore</actuatorUpid>
              <ParamInt>0</ParamInt>
              <ParamFloat>0</ParamFloat>
              <MaterialType>4096</MaterialType>
              <WaterType>-1</WaterType>
              <Indentation>2</Indentation>
              <ReScaleEnabled>false</ReScaleEnabled>
              <ReScale>1</ReScale>
              <HoldDistance>1</HoldDistance>
              <MaxHipoints>50</MaxHipoints>
              <MoveSpeedTileModifier>1</MoveSpeedTileModifier>
              <TurnSpeedTileModifier>1</TurnSpeedTileModifier>
              <WorldLightChangeEnabled>false</WorldLightChangeEnabled>
              <WorldLightChangeIndex>0</WorldLightChangeIndex>
              <WorldSkyChangeEnabled>false</WorldSkyChangeEnabled>
              <WorldSkyChangeIndex>0</WorldSkyChangeIndex>
              <SetWaterTypeIndex>-1</SetWaterTypeIndex>
              <filterUpids />
              <modifierUpids>
                <upid>modifier.scorebucket.color.white</upid>
                <upid>modifier.003points</upid>
              </modifierUpids>
              <SayMode>1</SayMode>
              <SayJustification>Left</SayJustification>
              <SaidString />
              <SaidMode>1</SaidMode>
              <SaidJustification>Left</SaidJustification>
              <MicrobitPatterns />
            </Reflex>
            <Reflex>
              <uniqueNum>179188</uniqueNum>
              <actuatorUpid>actuator.damage</actuatorUpid>
              <ParamInt>0</ParamInt>
              <ParamFloat>0</ParamFloat>
              <MaterialType>4096</MaterialType>
              <WaterType>-1</WaterType>
              <Indentation>3</Indentation>
              <ReScaleEnabled>false</ReScaleEnabled>
              <ReScale>1</ReScale>
              <HoldDistance>1</HoldDistance>
              <MaxHipoints>50</MaxHipoints>
              <MoveSpeedTileModifier>1</MoveSpeedTileModifier>
              <TurnSpeedTileModifier>1</TurnSpeedTileModifier>
              <WorldLightChangeEnabled>false</WorldLightChangeEnabled>
              <WorldLightChangeIndex>0</WorldLightChangeIndex>
              <WorldSkyChangeEnabled>false</WorldSkyChangeEnabled>
              <WorldSkyChangeIndex>0</WorldSkyChangeIndex>
              <SetWaterTypeIndex>-1</SetWaterTypeIndex>
              <filterUpids />
              <modifierUpids>
                <upid>modifier.003points</upid>
                <upid>modifier.me</upid>
              </modifierUpids>
              <SayMode>1</SayMode>
              <SayJustification>Left</SayJustification>
              <SaidString />
              <SaidMode>1</SaidMode>
              <SaidJustification>Left</SaidJustification>
              <MicrobitPatterns />
            </Reflex>
            <Reflex>
              <uniqueNum>179192</uniqueNum>
              <actuatorUpid>actuator.unscore</actuatorUpid>
              <ParamInt>0</ParamInt>
              <ParamFloat>0</ParamFloat>
              <MaterialType>4096</MaterialType>
              <WaterType>-1</WaterType>
              <Indentation>2</Indentation>
              <ReScaleEnabled>false</ReScaleEnabled>
              <ReScale>1</ReScale>
              <HoldDistance>1</HoldDistance>
              <MaxHipoints>50</MaxHipoints>
              <MoveSpeedTileModifier>1</MoveSpeedTileModifier>
              <TurnSpeedTileModifier>1</TurnSpeedTileModifier>
              <WorldLightChangeEnabled>false</WorldLightChangeEnabled>
              <WorldLightChangeIndex>0</WorldLightChangeIndex>
              <WorldSkyChangeEnabled>false</WorldSkyChangeEnabled>
              <WorldSkyChangeIndex>0</WorldSkyChangeIndex>
              <SetWaterTypeIndex>-1</SetWaterTypeIndex>
              <filterUpids />
              <modifierUpids>
                <upid>modifier.scorebucket.color.blue</upid>
                <upid>modifier.001point</upid>
              </modifierUpids>
              <SayMode>1</SayMode>
              <SayJustification>Left</SayJustification>
              <SaidString />
              <SaidMode>1</SaidMode>
              <SaidJustification>Left</SaidJustification>
              <MicrobitPatterns />
            </Reflex>
            <Reflex>
              <uniqueNum>179196</uniqueNum>
              <sensorUpid>sensor.missilehit</sensorUpid>
              <actuatorUpid>actuator.unscore</actuatorUpid>
              <ParamInt>0</ParamInt>
              <ParamFloat>0</ParamFloat>
              <MaterialType>4096</MaterialType>
              <WaterType>-1</WaterType>
              <Indentation>2</Indentation>
              <ReScaleEnabled>false</ReScaleEnabled>
              <ReScale>1</ReScale>
              <HoldDistance>1</HoldDistance>
              <MaxHipoints>50</MaxHipoints>
              <MoveSpeedTileModifier>1</MoveSpeedTileModifier>
              <TurnSpeedTileModifier>1</TurnSpeedTileModifier>
              <WorldLightChangeEnabled>false</WorldLightChangeEnabled>
              <WorldLightChangeIndex>0</WorldLightChangeIndex>
              <WorldSkyChangeEnabled>false</WorldSkyChangeEnabled>
              <WorldSkyChangeIndex>0</WorldSkyChangeIndex>
              <SetWaterTypeIndex>-1</SetWaterTypeIndex>
              <filterUpids>
                <upid>filter.me</upid>
              </filterUpids>
              <modifierUpids>
                <upid>modifier.scorebucket.color.white</upid>
                <upid>modifier.005points</upid>
              </modifierUpids>
              <SayMode>1</SayMode>
              <SayJustification>Left</SayJustification>
              <SaidString />
              <SaidMode>1</SaidMode>
              <SaidJustification>Left</SaidJustification>
              <MicrobitPatterns />
            </Reflex>
            <Reflex>
              <uniqueNum>179202</uniqueNum>
              <sensorUpid>sensor.health</sensorUpid>
              <actuatorUpid>actuator.victory</actuatorUpid>
              <ParamInt>0</ParamInt>
              <ParamFloat>0</ParamFloat>
              <MaterialType>4096</MaterialType>
              <WaterType>-1</WaterType>
              <Indentation>2</Indentation>
              <ReScaleEnabled>false</ReScaleEnabled>
              <ReScale>1</ReScale>
              <HoldDistance>1</HoldDistance>
              <MaxHipoints>50</MaxHipoints>
              <MoveSpeedTileModifier>1</MoveSpeedTileModifier>
              <TurnSpeedTileModifier>1</TurnSpeedTileModifier>
              <WorldLightChangeEnabled>false</WorldLightChangeEnabled>
              <WorldLightChangeIndex>0</WorldLightChangeIndex>
              <WorldSkyChangeEnabled>false</WorldSkyChangeEnabled>
              <WorldSkyChangeIndex>0</WorldSkyChangeIndex>
              <SetWaterTypeIndex>-1</SetWaterTypeIndex>
              <filterUpids>
                <upid>filter.scoreequals</upid>
                <upid>filter.000point</upid>
              </filterUpids>
              <modifierUpids>
                <upid>modifier.red</upid>
              </modifierUpids>
              <SayMode>1</SayMode>
              <SayJustification>Left</SayJustification>
              <SaidString />
              <SaidMode>1</SaidMode>
              <SaidJustification>Left</SaidJustification>
              <MicrobitPatterns />
            </Reflex>
          </reflexes>
        </Task>
        <Task upid="task.managed2">
          <reflexes />
        </Task>
        <Task upid="task.managed3">
          <reflexes />
        </Task>
        <Task upid="task.managed4">
          <reflexes />
        </Task>
        <Task upid="task.managed5">
          <reflexes />
        </Task>
        <Task upid="task.managed6">
          <reflexes />
        </Task>
        <Task upid="task.managed7">
          <reflexes />
        </Task>
        <Task upid="task.managed8">
          <reflexes />
        </Task>
        <Task upid="task.managed9">
          <reflexes />
        </Task>
        <Task upid="task.managed10">
          <reflexes />
        </Task>
        <Task upid="task.managed11">
          <reflexes />
        </Task>
      </tasks>
    </brain>
    <parameters>
      <uniqueNum>148210</uniqueNum>
      <immobile>false</immobile>
      <immobileNoRot>false</immobileNoRot>
      <invulnerable>false</invulnerable>
      <showSensors>false</showSensors>
      <showHitPoints>false</showHitPoints>
      <creatable>false</creatable>
      <mute>false</mute>
      <maxHitPoints>50</maxHitPoints>
      <blipDamage>5</blipDamage>
      <missileDamage>50</missileDamage>
      <movementSpeedModifier>1</movementSpeedModifier>
      <turningSpeedModifier>1</turningSpeedModifier>
      <linearAccelerationModifier>1</linearAccelerationModifier>
      <turningAccelerationModifier>1</turningAccelerationModifier>
      <verticalSpeedModifier>1</verticalSpeedModifier>
      <verticalAccelerationModifier>1</verticalAccelerationModifier>
      <blipReloadTime>0.05</blipReloadTime>
      <blipSpeed>10</blipSpeed>
      <blipRange>35</blipRange>
      <blipsInAir>40</blipsInAir>
      <beamReloadTime>0.025</beamReloadTime>
      <beamSpeed>10</beamSpeed>
      <beamDist>35</beamDist>
      <beamsInAir>2000</beamsInAir>
      <revealed>false</revealed>
      <missileReloadTime>3</missileReloadTime>
      <missileSpeed>6</missileSpeed>
      <missileRange>50</missileRange>
      <missilesInAir>4</missilesInAir>
      <missileTrails>true</missileTrails>
      <shieldEffects>true</shieldEffects>
      <invisible>false</invisible>
      <ignored>false</ignored>
      <camouflaged>false</camouflaged>
      <pushRange>15</pushRange>
      <pushStrength>50</pushStrength>
      <kickStrength>10</kickStrength>
      <kickRate>2</kickRate>
      <hearing>1</hearing>
      <loudness>1</loudness>
      <glowAmt>1</glowAmt>
      <glowLights>0</glowLights>
      <glowEmission>0</glowEmission>
      <displayLOS>false</displayLOS>
      <displayLOP>false</displayLOP>
      <displayCurrentPage>false</displayCurrentPage>
      <cameraMode>UserControlled</cameraMode>
      <coefficientOfRestitution>0.8</coefficientOfRestitution>
      <friction>0.5</friction>
      <lightRange>10</lightRange>
      <stayAboveWater>true</stayAboveWater>
      <maxCreated>1000</maxCreated>
      <rescale>0.5</rescale>
      <holdDistance>1</holdDistance>
      <_holdDistance>1</_holdDistance>
      <mass>10</mass>
      <heightOffset>-666</heightOffset>
      <nearByDistance>5</nearByDistance>
      <farAwayDistance>15</farAwayDistance>
    </parameters>
    <version>1</version>
    <typename>BokuBot</typename>
  </actor>
  <actor>
    <position>
      <X>-7.499503</X>
      <Y>9.678434</Y>
      <Z>0.787196159</Z>
    </position>
    <orientation>1.564821</orientation>
    <heightOffset>0</heightOffset>
    <color>Red</color>
    <tintable>true</tintable>
    <creatableId>00000000-0000-0000-0000-000000000000</creatableId>
    <creatableName>Kodu 2</creatableName>
    <brain StartTaskId="-1" ActiveTaskId="-1">
      <uniqueNum>179208</uniqueNum>
      <tasks>
        <Task upid="task.managed0">
          <reflexes />
        </Task>
        <Task upid="task.managed1">
          <reflexes />
        </Task>
        <Task upid="task.managed2">
          <reflexes />
        </Task>
        <Task upid="task.managed3">
          <reflexes />
        </Task>
        <Task upid="task.managed4">
          <reflexes />
        </Task>
        <Task upid="task.managed5">
          <reflexes />
        </Task>
        <Task upid="task.managed6">
          <reflexes />
        </Task>
        <Task upid="task.managed7">
          <reflexes />
        </Task>
        <Task upid="task.managed8">
          <reflexes />
        </Task>
        <Task upid="task.managed9">
          <reflexes />
        </Task>
        <Task upid="task.managed10">
          <reflexes />
        </Task>
        <Task upid="task.managed11">
          <reflexes />
        </Task>
      </tasks>
    </brain>
    <parameters>
      <uniqueNum>148235</uniqueNum>
      <immobile>false</immobile>
      <immobileNoRot>false</immobileNoRot>
      <invulnerable>false</invulnerable>
      <showSensors>false</showSensors>
      <showHitPoints>false</showHitPoints>
      <creatable>false</creatable>
      <mute>false</mute>
      <maxHitPoints>50</maxHitPoints>
      <blipDamage>5</blipDamage>
      <missileDamage>50</missileDamage>
      <movementSpeedModifier>1</movementSpeedModifier>
      <turningSpeedModifier>1</turningSpeedModifier>
      <linearAccelerationModifier>1</linearAccelerationModifier>
      <turningAccelerationModifier>1</turningAccelerationModifier>
      <verticalSpeedModifier>1</verticalSpeedModifier>
      <verticalAccelerationModifier>1</verticalAccelerationModifier>
      <blipReloadTime>0.05</blipReloadTime>
      <blipSpeed>10</blipSpeed>
      <blipRange>35</blipRange>
      <blipsInAir>40</blipsInAir>
      <beamReloadTime>0.025</beamReloadTime>
      <beamSpeed>10</beamSpeed>
      <beamDist>35</beamDist>
      <beamsInAir>2000</beamsInAir>
      <revealed>false</revealed>
      <missileReloadTime>3</missileReloadTime>
      <missileSpeed>6</missileSpeed>
      <missileRange>50</missileRange>
      <missilesInAir>4</missilesInAir>
      <missileTrails>true</missileTrails>
      <shieldEffects>true</shieldEffects>
      <invisible>false</invisible>
      <ignored>false</ignored>
      <camouflaged>false</camouflaged>
      <pushRange>15</pushRange>
      <pushStrength>50</pushStrength>
      <kickStrength>10</kickStrength>
      <kickRate>2</kickRate>
      <hearing>1</hearing>
      <loudness>1</loudness>
      <glowAmt>1</glowAmt>
      <glowLights>0</glowLights>
      <glowEmission>0</glowEmission>
      <displayLOS>false</displayLOS>
      <displayLOP>false</displayLOP>
      <displayCurrentPage>false</displayCurrentPage>
      <cameraMode>UserControlled</cameraMode>
      <coefficientOfRestitution>0.8</coefficientOfRestitution>
      <friction>0.5</friction>
      <lightRange>10</lightRange>
      <stayAboveWater>true</stayAboveWater>
      <maxCreated>1000</maxCreated>
      <rescale>0.3</rescale>
      <holdDistance>1</holdDistance>
      <_holdDistance>1</_holdDistance>
      <mass>10</mass>
      <heightOffset>-666</heightOffset>
      <nearByDistance>5</nearByDistance>
      <farAwayDistance>15</farAwayDistance>
    </parameters>
    <version>1</version>
    <typename>BokuBot</typename>
  </actor>
  <actor>
    <position>
      <X>-5.832344</X>
      <Y>16.1430264</Y>
      <Z>0.247196153</Z>
    </position>
    <orientation>1.564821</orientation>
    <heightOffset>0</heightOffset>
    <color>Orange</color>
    <tintable>true</tintable>
    <creatableId>00000000-0000-0000-0000-000000000000</creatableId>
    <creatableName>Rover 1</creatableName>
    <brain StartTaskId="-1" ActiveTaskId="-1">
      <uniqueNum>179209</uniqueNum>
      <tasks>
        <Task upid="task.managed0">
          <reflexes />
        </Task>
        <Task upid="task.managed1">
          <reflexes />
        </Task>
        <Task upid="task.managed2">
          <reflexes />
        </Task>
        <Task upid="task.managed3">
          <reflexes />
        </Task>
        <Task upid="task.managed4">
          <reflexes />
        </Task>
        <Task upid="task.managed5">
          <reflexes />
        </Task>
        <Task upid="task.managed6">
          <reflexes />
        </Task>
        <Task upid="task.managed7">
          <reflexes />
        </Task>
        <Task upid="task.managed8">
          <reflexes />
        </Task>
        <Task upid="task.managed9">
          <reflexes />
        </Task>
        <Task upid="task.managed10">
          <reflexes />
        </Task>
        <Task upid="task.managed11">
          <reflexes />
        </Task>
      </tasks>
    </brain>
    <parameters>
      <uniqueNum>148261</uniqueNum>
      <immobile>false</immobile>
      <immobileNoRot>false</immobileNoRot>
      <invulnerable>false</invulnerable>
      <showSensors>false</showSensors>
      <showHitPoints>false</showHitPoints>
      <creatable>false</creatable>
      <mute>false</mute>
      <maxHitPoints>50</maxHitPoints>
      <blipDamage>5</blipDamage>
      <missileDamage>50</missileDamage>
      <movementSpeedModifier>1</movementSpeedModifier>
      <turningSpeedModifier>1</turningSpeedModifier>
      <linearAccelerationModifier>1</linearAccelerationModifier>
      <turningAccelerationModifier>1</turningAccelerationModifier>
      <verticalSpeedModifier>1</verticalSpeedModifier>
      <verticalAccelerationModifier>1</verticalAccelerationModifier>
      <blipReloadTime>0.05</blipReloadTime>
      <blipSpeed>10</blipSpeed>
      <blipRange>35</blipRange>
      <blipsInAir>40</blipsInAir>
      <beamReloadTime>0.025</beamReloadTime>
      <beamSpeed>10</beamSpeed>
      <beamDist>35</beamDist>
      <beamsInAir>2000</beamsInAir>
      <revealed>false</revealed>
      <missileReloadTime>3</missileReloadTime>
      <missileSpeed>6</missileSpeed>
      <missileRange>50</missileRange>
      <missilesInAir>4</missilesInAir>
      <missileTrails>true</missileTrails>
      <shieldEffects>true</shieldEffects>
      <invisible>false</invisible>
      <ignored>false</ignored>
      <camouflaged>false</camouflaged>
      <pushRange>15</pushRange>
      <pushStrength>50</pushStrength>
      <kickStrength>10</kickStrength>
      <kickRate>2</kickRate>
      <hearing>1</hearing>
      <loudness>1</loudness>
      <glowAmt>1</glowAmt>
      <glowLights>0</glowLights>
      <glowEmission>0</glowEmission>
      <displayLOS>false</displayLOS>
      <displayLOP>false</displayLOP>
      <displayCurrentPage>false</displayCurrentPage>
      <cameraMode>UserControlled</cameraMode>
      <coefficientOfRestitution>0.8</coefficientOfRestitution>
      <friction>0.95</friction>
      <lightRange>10</lightRange>
      <stayAboveWater>true</stayAboveWater>
      <maxCreated>1000</maxCreated>
      <rescale>0.5</rescale>
      <holdDistance>1</holdDistance>
      <_holdDistance>1</_holdDistance>
      <mass>20</mass>
      <heightOffset>-666</heightOffset>
      <nearByDistance>5</nearByDistance>
      <farAwayDistance>15</farAwayDistance>
    </parameters>
    <version>1</version>
    <typename>Rover</typename>
  </actor>
  <actor>
    <position>
      <X>-1.98607445</X>
      <Y>11.8730574</Y>
      <Z>0.247196153</Z>
    </position>
    <orientation>1.564821</orientation>
    <heightOffset>0</heightOffset>
    <color>Blue</color>
    <tintable>true</tintable>
    <creatableId>00000000-0000-0000-0000-000000000000</creatableId>
    <creatableName>Rover 2</creatableName>
    <brain StartTaskId="-1" ActiveTaskId="-1">
      <uniqueNum>179210</uniqueNum>
      <tasks>
        <Task upid="task.managed0">
          <reflexes />
        </Task>
        <Task upid="task.managed1">
          <reflexes />
        </Task>
        <Task upid="task.managed2">
          <reflexes />
        </Task>
        <Task upid="task.managed3">
          <reflexes />
        </Task>
        <Task upid="task.managed4">
          <reflexes />
        </Task>
        <Task upid="task.managed5">
          <reflexes />
        </Task>
        <Task upid="task.managed6">
          <reflexes />
        </Task>
        <Task upid="task.managed7">
          <reflexes />
        </Task>
        <Task upid="task.managed8">
          <reflexes />
        </Task>
        <Task upid="task.managed9">
          <reflexes />
        </Task>
        <Task upid="task.managed10">
          <reflexes />
        </Task>
        <Task upid="task.managed11">
          <reflexes />
        </Task>
      </tasks>
    </brain>
    <parameters>
      <uniqueNum>148281</uniqueNum>
      <immobile>false</immobile>
      <immobileNoRot>false</immobileNoRot>
      <invulnerable>false</invulnerable>
      <showSensors>false</showSensors>
      <showHitPoints>false</showHitPoints>
      <creatable>false</creatable>
      <mute>false</mute>
      <maxHitPoints>50</maxHitPoints>
      <blipDamage>5</blipDamage>
      <missileDamage>50</missileDamage>
      <movementSpeedModifier>1</movementSpeedModifier>
      <turningSpeedModifier>1</turningSpeedModifier>
      <linearAccelerationModifier>1</linearAccelerationModifier>
      <turningAccelerationModifier>1</turningAccelerationModifier>
      <verticalSpeedModifier>1</verticalSpeedModifier>
      <verticalAccelerationModifier>1</verticalAccelerationModifier>
      <blipReloadTime>0.05</blipReloadTime>
      <blipSpeed>10</blipSpeed>
      <blipRange>35</blipRange>
      <blipsInAir>40</blipsInAir>
      <beamReloadTime>0.025</beamReloadTime>
      <beamSpeed>10</beamSpeed>
      <beamDist>35</beamDist>
      <beamsInAir>2000</beamsInAir>
      <revealed>false</revealed>
      <missileReloadTime>3</missileReloadTime>
      <missileSpeed>6</missileSpeed>
      <missileRange>50</missileRange>
      <missilesInAir>4</missilesInAir>
      <missileTrails>true</missileTrails>
      <shieldEffects>true</shieldEffects>
      <invisible>false</invisible>
      <ignored>false</ignored>
      <camouflaged>false</camouflaged>
      <pushRange>15</pushRange>
      <pushStrength>50</pushStrength>
      <kickStrength>10</kickStrength>
      <kickRate>2</kickRate>
      <hearing>1</hearing>
      <loudness>1</loudness>
      <glowAmt>1</glowAmt>
      <glowLights>0</glowLights>
      <glowEmission>0</glowEmission>
      <displayLOS>false</displayLOS>
      <displayLOP>false</displayLOP>
      <displayCurrentPage>false</displayCurrentPage>
      <cameraMode>UserControlled</cameraMode>
      <coefficientOfRestitution>0.8</coefficientOfRestitution>
      <friction>0.95</friction>
      <lightRange>10</lightRange>
      <stayAboveWater>true</stayAboveWater>
      <maxCreated>1000</maxCreated>
      <rescale>0.4</rescale>
      <holdDistance>1</holdDistance>
      <_holdDistance>1</_holdDistance>
      <mass>20</mass>
      <heightOffset>-666</heightOffset>
      <nearByDistance>5</nearByDistance>
      <farAwayDistance>15</farAwayDistance>
    </parameters>
    <version>1</version>
    <typename>Rover</typename>
  </actor>
  <actor>
    <position>
      <X>1.15447617</X>
      <Y>9.951393</Y>
      <Z>2.7471962</Z>
    </position>
    <orientation>1.564821</orientation>
    <heightOffset>0</heightOffset>
    <color>Red</color>
    <tintable>true</tintable>
    <creatableId>00000000-0000-0000-0000-000000000000</creatableId>
    <creatableName>Saucer 1</creatableName>
    <brain StartTaskId="-1" ActiveTaskId="-1">
      <uniqueNum>179211</uniqueNum>
      <tasks>
        <Task upid="task.managed0">
          <reflexes>
            <Reflex>
              <uniqueNum>179212</uniqueNum>
              <sensorUpid>sensor.always</sensorUpid>
              <selectorUpid>selector.followwaypoints</selectorUpid>
              <actuatorUpid>actuator.movement</actuatorUpid>
              <ParamInt>0</ParamInt>
              <ParamFloat>0</ParamFloat>
              <MaterialType>4096</MaterialType>
              <WaterType>-1</WaterType>
              <Indentation>0</Indentation>
              <ReScaleEnabled>false</ReScaleEnabled>
              <ReScale>1</ReScale>
              <HoldDistance>1</HoldDistance>
              <MaxHipoints>50</MaxHipoints>
              <MoveSpeedTileModifier>1</MoveSpeedTileModifier>
              <TurnSpeedTileModifier>1</TurnSpeedTileModifier>
              <WorldLightChangeEnabled>false</WorldLightChangeEnabled>
              <WorldLightChangeIndex>0</WorldLightChangeIndex>
              <WorldSkyChangeEnabled>false</WorldSkyChangeEnabled>
              <WorldSkyChangeIndex>0</WorldSkyChangeIndex>
              <SetWaterTypeIndex>-1</SetWaterTypeIndex>
              <filterUpids />
              <modifierUpids>
                <upid>modifier.path.red</upid>
              </modifierUpids>
              <SayMode>1</SayMode>
              <SayJustification>Left</SayJustification>
              <SaidString />
              <SaidMode>1</SaidMode>
              <SaidJustification>Left</SaidJustification>
              <MicrobitPatterns />
            </Reflex>
            <Reflex>
              <uniqueNum>179217</uniqueNum>
              <sensorUpid>sensor.eyes</sensorUpid>
              <actuatorUpid>actuator.shoot2</actuatorUpid>
              <ParamInt>0</ParamInt>
              <ParamFloat>0</ParamFloat>
              <MaterialType>4096</MaterialType>
              <WaterType>-1</WaterType>
              <Indentation>0</Indentation>
              <ReScaleEnabled>false</ReScaleEnabled>
              <ReScale>1</ReScale>
              <HoldDistance>1</HoldDistance>
              <MaxHipoints>50</MaxHipoints>
              <MoveSpeedTileModifier>1</MoveSpeedTileModifier>
              <TurnSpeedTileModifier>1</TurnSpeedTileModifier>
              <WorldLightChangeEnabled>false</WorldLightChangeEnabled>
              <WorldLightChangeIndex>0</WorldLightChangeIndex>
              <WorldSkyChangeEnabled>false</WorldSkyChangeEnabled>
              <WorldSkyChangeIndex>0</WorldSkyChangeIndex>
              <SetWaterTypeIndex>-1</SetWaterTypeIndex>
              <filterUpids>
                <upid>filter.bokubot</upid>
                <upid>filter.closeby</upid>
              </filterUpids>
              <modifierUpids>
                <upid>modifier.projectile.missile</upid>
                <upid>modifier.trackingnone</upid>
              </modifierUpids>
              <SayMode>1</SayMode>
              <SayJustification>Left</SayJustification>
              <SaidString />
              <SaidMode>1</SaidMode>
              <SaidJustification>Left</SaidJustification>
              <MicrobitPatterns />
            </Reflex>
          </reflexes>
        </Task>
        <Task upid="task.managed1">
          <reflexes />
        </Task>
        <Task upid="task.managed2">
          <reflexes />
        </Task>
        <Task upid="task.managed3">
          <reflexes />
        </Task>
        <Task upid="task.managed4">
          <reflexes />
        </Task>
        <Task upid="task.managed5">
          <reflexes />
        </Task>
        <Task upid="task.managed6">
          <reflexes />
        </Task>
        <Task upid="task.managed7">
          <reflexes />
        </Task>
        <Task upid="task.managed8">
          <reflexes />
        </Task>
        <Task upid="task.managed9">
          <reflexes />
        </Task>
        <Task upid="task.managed10">
          <reflexes />
        </Task>
        <Task upid="task.managed11">
          <reflexes />
        </Task>
      </tasks>
    </brain>
    <parameters>
      <uniqueNum>148322</uniqueNum>
      <immobile>false</immobile>
      <immobileNoRot>false</immobileNoRot>
      <invulnerable>false</invulnerable>
      <showSensors>false</showSensors>
      <showHitPoints>false</showHitPoints>
      <creatable>false</creatable>
      <mute>false</mute>
      <maxHitPoints>50</maxHitPoints>
      <blipDamage>5</blipDamage>
      <missileDamage>50</missileDamage>
      <movementSpeedModifier>1</movementSpeedModifier>
      <turningSpeedModifier>1</turningSpeedModifier>
      <linearAccelerationModifier>1</linearAccelerationModifier>
      <turningAccelerationModifier>1</turningAccelerationModifier>
      <verticalSpeedModifier>1</verticalSpeedModifier>
      <verticalAccelerationModifier>1</verticalAccelerationModifier>
      <blipReloadTime>0.05</blipReloadTime>
      <blipSpeed>10</blipSpeed>
      <blipRange>35</blipRange>
      <blipsInAir>40</blipsInAir>
      <beamReloadTime>0.025</beamReloadTime>
      <beamSpeed>10</beamSpeed>
      <beamDist>35</beamDist>
      <beamsInAir>2000</beamsInAir>
      <revealed>false</revealed>
      <missileReloadTime>3</missileReloadTime>
      <missileSpeed>6</missileSpeed>
      <missileRange>50</missileRange>
      <missilesInAir>4</missilesInAir>
      <missileTrails>true</missileTrails>
      <shieldEffects>true</shieldEffects>
      <invisible>false</invisible>
      <ignored>false</ignored>
      <camouflaged>false</camouflaged>
      <pushRange>15</pushRange>
      <pushStrength>50</pushStrength>
      <kickStrength>10</kickStrength>
      <kickRate>2</kickRate>
      <hearing>1</hearing>
      <loudness>1</loudness>
      <glowAmt>1</glowAmt>
      <glowLights>0</glowLights>
      <glowEmission>0</glowEmission>
      <displayLOS>false</displayLOS>
      <displayLOP>false</displayLOP>
      <displayCurrentPage>false</displayCurrentPage>
      <cameraMode>UserControlled</cameraMode>
      <coefficientOfRestitution>0.8</coefficientOfRestitution>
      <friction>0.5</friction>
      <lightRange>10</lightRange>
      <stayAboveWater>true</stayAboveWater>
      <maxCreated>1000</maxCreated>
      <rescale>0.5</rescale>
      <holdDistance>1</holdDistance>
      <_holdDistance>1</_holdDistance>
      <mass>20</mass>
      <heightOffset>-666</heightOffset>
      <nearByDistance>5</nearByDistance>
      <farAwayDistance>15</farAwayDistance>
    </parameters>
    <version>1</version>
    <typename>Saucer</typename>
  </actor>
  <actor>
    <position>
      <X>-8.188047</X>
      <Y>18.856369</Y>
      <Z>0.337196052</Z>
    </position>
    <orientation>1.564821</orientation>
    <heightOffset>-2.41</heightOffset>
    <color>White</color>
    <tintable>true</tintable>
    <creatableId>00000000-0000-0000-0000-000000000000</creatableId>
    <creatableName>Saucer 2</creatableName>
    <brain StartTaskId="-1" ActiveTaskId="-1">
      <uniqueNum>179224</uniqueNum>
      <tasks>
        <Task upid="task.managed0">
          <reflexes>
            <Reflex>
              <uniqueNum>179225</uniqueNum>
              <sensorUpid>sensor.always</sensorUpid>
              <selectorUpid>selector.followwaypoints</selectorUpid>
              <actuatorUpid>actuator.movement</actuatorUpid>
              <ParamInt>0</ParamInt>
              <ParamFloat>0</ParamFloat>
              <MaterialType>4096</MaterialType>
              <WaterType>-1</WaterType>
              <Indentation>0</Indentation>
              <ReScaleEnabled>false</ReScaleEnabled>
              <ReScale>1</ReScale>
              <HoldDistance>1</HoldDistance>
              <MaxHipoints>50</MaxHipoints>
              <MoveSpeedTileModifier>1</MoveSpeedTileModifier>
              <TurnSpeedTileModifier>1</TurnSpeedTileModifier>
              <WorldLightChangeEnabled>false</WorldLightChangeEnabled>
              <WorldLightChangeIndex>0</WorldLightChangeIndex>
              <WorldSkyChangeEnabled>false</WorldSkyChangeEnabled>
              <WorldSkyChangeIndex>0</WorldSkyChangeIndex>
              <SetWaterTypeIndex>-1</SetWaterTypeIndex>
              <filterUpids />
              <modifierUpids>
                <upid>modifier.path.white</upid>
              </modifierUpids>
              <SayMode>1</SayMode>
              <SayJustification>Left</SayJustification>
              <SaidString />
              <SaidMode>1</SaidMode>
              <SaidJustification>Left</SaidJustification>
              <MicrobitPatterns />
            </Reflex>
            <Reflex>
              <uniqueNum>179230</uniqueNum>
              <sensorUpid>sensor.eyes</sensorUpid>
              <actuatorUpid>actuator.shoot2</actuatorUpid>
              <ParamInt>0</ParamInt>
              <ParamFloat>0</ParamFloat>
              <MaterialType>4096</MaterialType>
              <WaterType>-1</WaterType>
              <Indentation>0</Indentation>
              <ReScaleEnabled>false</ReScaleEnabled>
              <ReScale>1</ReScale>
              <HoldDistance>1</HoldDistance>
              <MaxHipoints>50</MaxHipoints>
              <MoveSpeedTileModifier>1</MoveSpeedTileModifier>
              <TurnSpeedTileModifier>1</TurnSpeedTileModifier>
              <WorldLightChangeEnabled>false</WorldLightChangeEnabled>
              <WorldLightChangeIndex>0</WorldLightChangeIndex>
              <WorldSkyChangeEnabled>false</WorldSkyChangeEnabled>
              <WorldSkyChangeIndex>0</WorldSkyChangeIndex>
              <SetWaterTypeIndex>-1</SetWaterTypeIndex>
              <filterUpids>
                <upid>filter.bokubot</upid>
                <upid>filter.closeby</upid>
              </filterUpids>
              <modifierUpids>
                <upid>modifier.projectile.missile</upid>
                <upid>modifier.trackingnone</upid>
              </modifierUpids>
              <SayMode>1</SayMode>
              <SayJustification>Left</SayJustification>
              <SaidString />
              <SaidMode>1</SaidMode>
              <SaidJustification>Left</SaidJustification>
              <MicrobitPatterns />
            </Reflex>
          </reflexes>
        </Task>
        <Task upid="task.managed1">
          <reflexes />
        </Task>
        <Task upid="task.managed2">
          <reflexes />
        </Task>
        <Task upid="task.managed3">
          <reflexes />
        </Task>
        <Task upid="task.managed4">
          <reflexes />
        </Task>
        <Task upid="task.managed5">
          <reflexes />
        </Task>
        <Task upid="task.managed6">
          <reflexes />
        </Task>
        <Task upid="task.managed7">
          <reflexes />
        </Task>
        <Task upid="task.managed8">
          <reflexes />
        </Task>
        <Task upid="task.managed9">
          <reflexes />
        </Task>
        <Task upid="task.managed10">
          <reflexes />
        </Task>
        <Task upid="task.managed11">
          <reflexes />
        </Task>
      </tasks>
    </brain>
    <parameters>
      <uniqueNum>148351</uniqueNum>
      <immobile>false</immobile>
      <immobileNoRot>false</immobileNoRot>
      <invulnerable>false</invulnerable>
      <showSensors>false</showSensors>
      <showHitPoints>false</showHitPoints>
      <creatable>false</creatable>
      <mute>false</mute>
      <maxHitPoints>50</maxHitPoints>
      <blipDamage>5</blipDamage>
      <missileDamage>50</missileDamage>
      <movementSpeedModifier>1</movementSpeedModifier>
      <turningSpeedModifier>1</turningSpeedModifier>
      <linearAccelerationModifier>1</linearAccelerationModifier>
      <turningAccelerationModifier>1</turningAccelerationModifier>
      <verticalSpeedModifier>1</verticalSpeedModifier>
      <verticalAccelerationModifier>1</verticalAccelerationModifier>
      <blipReloadTime>0.05</blipReloadTime>
      <blipSpeed>10</blipSpeed>
      <blipRange>35</blipRange>
      <blipsInAir>40</blipsInAir>
      <beamReloadTime>0.025</beamReloadTime>
      <beamSpeed>10</beamSpeed>
      <beamDist>35</beamDist>
      <beamsInAir>2000</beamsInAir>
      <revealed>false</revealed>
      <missileReloadTime>3</missileReloadTime>
      <missileSpeed>6</missileSpeed>
      <missileRange>50</missileRange>
      <missilesInAir>4</missilesInAir>
      <missileTrails>true</missileTrails>
      <shieldEffects>true</shieldEffects>
      <invisible>false</invisible>
      <ignored>false</ignored>
      <camouflaged>false</camouflaged>
      <pushRange>15</pushRange>
      <pushStrength>50</pushStrength>
      <kickStrength>10</kickStrength>
      <kickRate>2</kickRate>
      <hearing>1</hearing>
      <loudness>1</loudness>
      <glowAmt>1</glowAmt>
      <glowLights>0</glowLights>
      <glowEmission>0</glowEmission>
      <displayLOS>false</displayLOS>
      <displayLOP>false</displayLOP>
      <displayCurrentPage>false</displayCurrentPage>
      <cameraMode>UserControlled</cameraMode>
      <coefficientOfRestitution>0.8</coefficientOfRestitution>
      <friction>0.5</friction>
      <lightRange>10</lightRange>
      <stayAboveWater>true</stayAboveWater>
      <maxCreated>1000</maxCreated>
      <rescale>0.5</rescale>
      <holdDistance>1</holdDistance>
      <_holdDistance>1</_holdDistance>
      <mass>20</mass>
      <heightOffset>-666</heightOffset>
      <nearByDistance>5</nearByDistance>
      <farAwayDistance>15</farAwayDistance>
    </parameters>
    <version>1</version>
    <typename>Saucer</typename>
  </actor>
</XmlLevelData>